AUTHORS
LICENSE
MANIFEST.in
README.rst
bootstrap.py
buildout.cfg
conftest.py
makefile
setup.cfg
setup.py
tests.py
tox.ini
tools/mongodb-install
waterboy/__init__.py
waterboy/backends.py
waterboy/config.py
waterboy/testing.py
waterboy/utils.py
waterboy.egg-info/PKG-INFO
waterboy.egg-info/SOURCES.txt
waterboy.egg-info/dependency_links.txt
waterboy.egg-info/not-zip-safe
waterboy.egg-info/requires.txt
waterboy.egg-info/top_level.txt