Metadata-Version: 1.1
Name: waterboy
Version: 0.1.0
Summary: Live application settings with pluggable backends, including Redis and MongoDB.
Home-page: http://github.com/gmflanagan/waterboy
Author: Jerd Flanagan
Author-email: gmflanagan@outlook.com
License: BSD
Keywords: libraries,settings,redis,mongodb
Platform: any
Classifier: Development Status :: 5 - Production/Stable
Classifier: Environment :: Web Environment
Classifier: Framework :: Django
Classifier: Intended Audience :: Developers
Classifier: Natural Language :: English
Classifier: License :: OSI Approved :: BSD License
Classifier: Operating System :: OS Independent
Classifier: Programming Language :: Python
Classifier: Programming Language :: Python :: 2
Classifier: Programming Language :: Python :: 2.7
Classifier: Programming Language :: Python :: 3
Classifier: Programming Language :: Python :: 3.4
Classifier: Topic :: Utilities
